{
  "$schema": "http://json-schema.org/draft-07/schema#",
  "type": "object",
  "description": "Resource Type definition for AWS::Connect::Queue",
  "definitions": {
    "OutboundCallerIdName": {
      "oneOf": [
        {
          "type": "string",
          "minLength": 1,
          "maxLength": 255
        },
        {
          "$ref": "../component/functions.json#/AwsFunctionString"
        }
      ],
      "description": "The caller ID name."
    },
    "OutboundCallerIdNumberArn": {
      "oneOf": [
        {
          "type": "string",
          "pattern": "^arn:aws[-a-z0-9]*:connect:[-a-z0-9]*:[0-9]{12}:phone-number/[-a-zA-Z0-9]*$"
        },
        {
          "$ref": "../component/functions.json#/AwsFunctionString"
        }
      ],
      "description": "The caller ID number."
    },
    "OutboundFlowArn": {
      "oneOf": [
        {
          "type": "string",
          "pattern": "^arn:aws[-a-z0-9]*:connect:[-a-z0-9]*:[0-9]{12}:instance/[-a-zA-Z0-9]*/contact-flow/[-a-zA-Z0-9]*$",
          "minLength": 1,
          "maxLength": 500
        },
        {
          "$ref": "../component/functions.json#/AwsFunctionString"
        }
      ],
      "description": "The outbound whisper flow to be used during an outbound call."
    },
    "Tag": {
      "description": "A key-value pair to associate with a resource.",
      "type": "object",
      "properties": {
        "Key": {
          "$ref": "#/definitions/Key"
        },
        "Value": {
          "$ref": "#/definitions/Value"
        }
      },
      "required": [
        "Key",
        "Value"
      ],
      "additionalProperties": false
    },
    "Key": {
      "oneOf": [
        {
          "type": "string",
          "minLength": 1,
          "maxLength": 128,
          "pattern": "^(?!aws:)[a-zA-Z+-=._:/]+$"
        },
        {
          "$ref": "../component/functions.json#/AwsFunctionString"
        }
      ],
      "description": "The key name of the tag. You can specify a value that is 1 to 128 Unicode characters in length and cannot be prefixed with aws:. You can use any of the following characters: the set of Unicode letters, digits, whitespace, _, ., /, =, +, and -."
    },
    "Value": {
      "oneOf": [
        {
          "type": "string",
          "minLength": 0,
          "maxLength": 256
        },
        {
          "$ref": "../component/functions.json#/AwsFunctionString"
        }
      ],
      "description": "The value for the tag. You can specify a value that is 0 to 256 Unicode characters in length and cannot be prefixed with aws:. You can use any of the following characters: the set of Unicode letters, digits, whitespace, _, ., /, =, +, and -."
    },
    "OutboundCallerConfig": {
      "description": "The outbound caller ID name, number, and outbound whisper flow.",
      "type": "object",
      "additionalProperties": false,
      "properties": {
        "OutboundCallerIdName": {
          "$ref": "#/definitions/OutboundCallerIdName"
        },
        "OutboundCallerIdNumberArn": {
          "$ref": "#/definitions/OutboundCallerIdNumberArn"
        },
        "OutboundFlowArn": {
          "$ref": "#/definitions/OutboundFlowArn"
        }
      }
    },
    "QuickConnectArn": {
      "oneOf": [
        {
          "type": "string",
          "pattern": "^arn:aws[-a-z0-9]*:connect:[-a-z0-9]*:[0-9]{12}:instance/[-a-zA-Z0-9]*/transfer-destination/[-a-zA-Z0-9]*$"
        },
        {
          "$ref": "../component/functions.json#/AwsFunctionString"
        }
      ],
      "description": "The Amazon Resource Name (ARN) for the quick connect."
    }
  },
  "properties": {
    "InstanceArn": {
      "oneOf": [
        {
          "type": "string",
          "pattern": "^arn:aws[-a-z0-9]*:connect:[-a-z0-9]*:[0-9]{12}:instance/[-a-zA-Z0-9]*$"
        },
        {
          "$ref": "../component/functions.json#/AwsFunctionString"
        }
      ],
      "description": "The identifier of the Amazon Connect instance."
    },
    "Description": {
      "oneOf": [
        {
          "type": "string",
          "minLength": 1,
          "maxLength": 250
        },
        {
          "$ref": "../component/functions.json#/AwsFunctionString"
        }
      ],
      "description": "The description of the queue."
    },
    "HoursOfOperationArn": {
      "oneOf": [
        {
          "type": "string",
          "pattern": "^arn:aws[-a-z0-9]*:connect:[-a-z0-9]*:[0-9]{12}:instance/[-a-zA-Z0-9]*/operating-hours/[-a-zA-Z0-9]*$"
        },
        {
          "$ref": "../component/functions.json#/AwsFunctionString"
        }
      ],
      "description": "The identifier for the hours of operation."
    },
    "MaxContacts": {
      "description": "The maximum number of contacts that can be in the queue before it is considered full.",
      "type": "integer",
      "minimum": 0
    },
    "Name": {
      "oneOf": [
        {
          "type": "string",
          "minLength": 1,
          "maxLength": 127
        },
        {
          "$ref": "../component/functions.json#/AwsFunctionString"
        }
      ],
      "description": "The name of the queue."
    },
    "OutboundCallerConfig": {
      "description": "The outbound caller ID name, number, and outbound whisper flow.",
      "$ref": "#/definitions/OutboundCallerConfig"
    },
    "QueueArn": {
      "oneOf": [
        {
          "type": "string",
          "pattern": "^arn:aws[-a-z0-9]*:connect:[-a-z0-9]*:[0-9]{12}:instance/[-a-zA-Z0-9]*/queue/[-a-zA-Z0-9]*$"
        },
        {
          "$ref": "../component/functions.json#/AwsFunctionString"
        }
      ],
      "description": "The Amazon Resource Name (ARN) for the queue."
    },
    "Status": {
      "oneOf": [
        {
          "type": "string",
          "enum": [
            "ENABLED",
            "DISABLED"
          ]
        },
        {
          "$ref": "../component/functions.json#/AwsFunctionString"
        }
      ],
      "description": "The status of the queue."
    },
    "QuickConnectArns": {
      "description": "The quick connects available to agents who are working the queue.",
      "type": "array",
      "minItems": 1,
      "maxItems": 50,
      "insertionOrder": false,
      "items": {
        "$ref": "#/definitions/QuickConnectArn"
      }
    },
    "Tags": {
      "type": "array",
      "maxItems": 50,
      "uniqueItems": true,
      "insertionOrder": false,
      "description": "An array of key-value pairs to apply to this resource.",
      "items": {
        "$ref": "#/definitions/Tag"
      }
    },
    "Type": {
      "oneOf": [
        {
          "type": "string",
          "enum": [
            "STANDARD",
            "AGENT"
          ]
        },
        {
          "$ref": "../component/functions.json#/AwsFunctionString"
        }
      ],
      "description": "The type of queue."
    }
  },
  "additionalProperties": false,
  "required": [
    "InstanceArn",
    "HoursOfOperationArn",
    "Name"
  ]
}