{
  "$schema": "http://json-schema.org/draft-07/schema#",
  "type": "object",
  "description": "Resource Type definition for AWS::Connect::ApprovedOrigin",
  "definitions": {
    "Origin": {
      "oneOf": [
        {
          "type": "string",
          "maxLength": 267
        },
        {
          "$ref": "../component/functions.json#/AwsFunctionString"
        }
      ],
      "description": "Domain name to be added to the allowlist of instance"
    },
    "InstanceId": {
      "oneOf": [
        {
          "type": "string",
          "pattern": "^arn:aws[-a-z0-9]*:connect:[-a-z0-9]*:[0-9]{12}:instance/[-a-zA-Z0-9]*$",
          "minLength": 1,
          "maxLength": 100
        },
        {
          "$ref": "../component/functions.json#/AwsFunctionString"
        }
      ],
      "description": "Amazon Connect instance identifier"
    }
  },
  "properties": {
    "Origin": {
      "$ref": "#/definitions/Origin"
    },
    "InstanceId": {
      "$ref": "#/definitions/InstanceId"
    }
  },
  "additionalProperties": false,
  "required": [
    "Origin",
    "InstanceId"
  ]
}