{
  "$schema": "http://json-schema.org/draft-07/schema#",
  "type": "object",
  "description": "resource definition",
  "definitions": {
    "Tag": {
      "description": "A key-value pair to associate with a resource.",
      "type": "object",
      "properties": {
        "Key": {
          "oneOf": [
            {
              "type": "string",
              "minLength": 1,
              "maxLength": 128,
              "pattern": "^([\\p{L}\\p{Z}\\p{N}_.:/=+\\-@]*)$"
            },
            {
              "$ref": "../component/functions.json#/AwsFunctionString"
            }
          ],
          "description": "The key name of the tag. You can specify a value that is 1 to 128 Unicode characters in length and cannot be prefixed with aws:. You can use any of the following characters: the set of Unicode letters, digits, whitespace, _, ., /, =, +, and -. "
        },
        "Value": {
          "oneOf": [
            {
              "type": "string",
              "minLength": 1,
              "maxLength": 256
            },
            {
              "$ref": "../component/functions.json#/AwsFunctionString"
            }
          ],
          "description": "The value for the tag. You can specify a value that is 1 to 256 Unicode characters in length and cannot be prefixed with aws:. You can use any of the following characters: the set of Unicode letters, digits, whitespace, _, ., /, =, +, and -. "
        }
      },
      "required": [
        "Key",
        "Value"
      ],
      "additionalProperties": false
    }
  },
  "properties": {
    "Description": {
      "oneOf": [
        {
          "type": "string",
          "maxLength": 1024,
          "minLength": 0,
          "pattern": "^[^\\p{C}]+$"
        },
        {
          "$ref": "../component/functions.json#/AwsFunctionString"
        }
      ]
    },
    "PackageArn": {
      "oneOf": [
        {
          "type": "string"
        },
        {
          "$ref": "../component/functions.json#/AwsFunctionString"
        }
      ]
    },
    "PackageName": {
      "oneOf": [
        {
          "type": "string",
          "maxLength": 128,
          "minLength": 1,
          "pattern": "^[a-zA-Z0-9-_.]+$"
        },
        {
          "$ref": "../component/functions.json#/AwsFunctionString"
        }
      ]
    },
    "Tags": {
      "description": "An array of key-value pairs to apply to this resource.",
      "type": "array",
      "maxItems": 50,
      "uniqueItems": true,
      "insertionOrder": false,
      "items": {
        "$ref": "#/definitions/Tag"
      }
    }
  },
  "additionalProperties": false
}